pytest_pretty_terminal/__init__.py
pytest_pretty_terminal/_pretty_terminal_reporter.py
pytest_pretty_terminal/py.typed
pytest_pretty_terminal-1.1.0.dist-info/METADATA
pytest_pretty_terminal-1.1.0.dist-info/WHEEL
pytest_pretty_terminal-1.1.0.dist-info/entry_points.txt
pytest_pretty_terminal-1.1.0.dist-info/top_level.txt
pytest_pretty_terminal-1.1.0.dist-info/RECORD
