Metadata-Version: 2.1
Name: pytest-pretty-terminal
Version: 1.1.0
Summary: pytest plugin for generating prettier terminal output
Home-page: https://github.com/devolo/pytest-adaptavist
Author: Stephan Steinberg, Markus Bong, Guido Schmitz
Author-email: markus.bong@devolo.de, guido.schmitz@devolo.de
License: MIT
Keywords: python pytest adaptavist kanoah tm4j jira test testmanagement report
Platform: any
Classifier: Framework :: Pytest
Classifier: Intended Audience :: Developers
Classifier: License :: OSI Approved :: MIT License
Classifier: Operating System :: OS Independent
Classifier: Programming Language :: Python
Classifier: Programming Language :: Python :: 3
Classifier: Topic :: Software Development :: Quality Assurance
Classifier: Topic :: Software Development :: Testing
Classifier: Topic :: Utilities
Classifier: Topic :: Software Development :: Libraries :: Python Modules
Requires-Python: >=3.8
Requires-Dist: pytest (>=3.4.1)
Provides-Extra: test
Requires-Dist: pytest-adaptavist (>=5.1.1) ; extra == 'test'
